colourin/__init__.py
colourin/thing.py
colourin-1.3.0.dist-info/METADATA
colourin-1.3.0.dist-info/WHEEL
colourin-1.3.0.dist-info/top_level.txt
colourin-1.3.0.dist-info/RECORD
